setup.py
django_internal_urls/__init__.py
django_internal_urls/autoload.py
django_internal_urls/defaultmodules.py
django_internal_urls/models.py
django_internal_urls/modules.py
django_internal_urls/settings.py
django_internal_urls/utils.py
django_internal_urls.egg-info/PKG-INFO
django_internal_urls.egg-info/SOURCES.txt
django_internal_urls.egg-info/dependency_links.txt
django_internal_urls.egg-info/requires.txt
django_internal_urls.egg-info/top_level.txt
django_internal_urls/templatetags/__init__.py
django_internal_urls/templatetags/internal_urls.py