Metadata-Version: 1.1
Name: django-internal-urls
Version: 0.1.0-2
Summary: Add modular url callbacks
Home-page: https://github.com/ddanier/django_internal_urls
Author: David Danier
Author-email: david.danier@team23.de
License: UNKNOWN
Platform: UNKNOWN
Classifier: Development Status :: 4 - Beta
Classifier: Environment :: Web Environment
Classifier: Framework :: Django
Classifier: Intended Audience :: Developers
Classifier: License :: OSI Approved :: BSD License
Classifier: Operating System :: OS Independent
Classifier: Programming Language :: Python
Classifier: Topic :: Utilities
